cohorts/__init__.py
cohorts/generator.py
cohorts/models/__init__.py
cohorts/models/data/__init__.py
cohorts/models/data/entry.py
cohorts/models/data/member.py
cohorts/models/data/simple_pass.py
cohorts/models/filters/__init__.py
cohorts/models/filters/single_category.py
cohorts/models/metrics/__init__.py
cohorts/models/metrics/basic.py
cohorts/models/timestep/__init__.py
cohorts/models/timestep/standard.py
examples/__init__.py
examples/three_sided_marketplace/__init__.py
examples/three_sided_marketplace/marketplace.py
f27_cohorts-1.0.0.dist-info/DESCRIPTION.rst
f27_cohorts-1.0.0.dist-info/METADATA
f27_cohorts-1.0.0.dist-info/RECORD
f27_cohorts-1.0.0.dist-info/WHEEL
f27_cohorts-1.0.0.dist-info/metadata.json
f27_cohorts-1.0.0.dist-info/top_level.txt
