Metadata-Version: 2.0
Name: f27-cohorts
Version: 1.0.0
Summary: Make cohort analysis a magical experience
Home-page: https://github.com/F27Ventures/cohorts
Author: F27 Ventures
Author-email: dev@f27.ventures
License: UNKNOWN
